PyBetterGitUp/__init__.py
PyBetterGitUp/bgitup.py
PyBetterGitUp/version.py
PyBetterGitUp-0.7.1.data/scripts/bgitup.py
PyBetterGitUp-0.7.1.dist-info/LICENSE
PyBetterGitUp-0.7.1.dist-info/METADATA
PyBetterGitUp-0.7.1.dist-info/WHEEL
PyBetterGitUp-0.7.1.dist-info/entry_points.txt
PyBetterGitUp-0.7.1.dist-info/top_level.txt
PyBetterGitUp-0.7.1.dist-info/RECORD
