Metadata-Version: 2.1
Name: PyBetterGitUp
Version: 0.7.1
Summary: A better package for git up
Home-page: https://github.com/edweird06/BetterGitUp
Author: Edward Taylor
Author-email: edweird06@users.noreply.github.com
License: UNKNOWN
Platform: UNKNOWN
Classifier: Programming Language :: Python :: 3
Classifier: License :: OSI Approved :: MIT License
Classifier: Operating System :: OS Independent
Requires-Python: >=3.6
Requires-Dist: GitPython (==3.1.7)
Requires-Dist: git-up (==1.6.1)
Requires-Dist: colorama (>=0.4.3)
Requires-Dist: gitversion (==2.1.3)
